obl/__init__.py
obl-1.0.0.dist-info/LICENSE
obl-1.0.0.dist-info/METADATA
obl-1.0.0.dist-info/WHEEL
obl-1.0.0.dist-info/top_level.txt
obl-1.0.0.dist-info/RECORD
