Metadata-Version: 2.1
Name: obl
Version: 1.0.0
Summary: Library to interact with OBL from host side
Home-page: https://github.com/sebastien-riou/OBL
Author: Sebastien Riou
Author-email: sebastien.riou@tiempo-secure.com
License: UNKNOWN
Platform: UNKNOWN
Classifier: Programming Language :: Python :: 3
Classifier: Operating System :: OS Independent
Requires-Dist: pysatl (>=1.2.5)
